proto_agent/Config.py
proto_agent/__init__.py
proto_agent/agent.py
proto_agent/agent_settings.py
proto_agent/main.py
proto_agent/tool_kit_registry.py
proto_agent/tool_kits/__init__.py
proto_agent/tool_kits/base_toolkit.py
proto_agent/tool_kits/file_operation_toolkit.py
proto_agent/tool_kits/git_toolkit.py
proto_agent/tool_kits/system_info_toolkit.py
proto_agent/types_llm.py
proto_agent-0.7.1.dist-info/WHEEL
proto_agent-0.7.1.dist-info/entry_points.txt
proto_agent-0.7.1.dist-info/METADATA
proto_agent-0.7.1.dist-info/RECORD
