Metadata-Version: 2.3
Name: proto-agent
Version: 0.7.1
Summary: A modular AI agent framework that can also be your local CLI agent!
Keywords: ai,agent,modular,automation,library,framework,CLI
Author: WeismannS
Author-email: WeismannS <Sahazell@proton.me>
License: MIT
Classifier: Development Status :: 4 - Beta
Classifier: Intended Audience :: Developers
Classifier: License :: OSI Approved :: MIT License
Classifier: Programming Language :: Python :: 3
Classifier: Programming Language :: Python :: 3.10
Classifier: Programming Language :: Python :: 3.11
Classifier: Programming Language :: Python :: 3.12
Classifier: Topic :: Software Development :: Libraries
Classifier: Topic :: Utilities
Requires-Dist: click>=8.2.1
Requires-Dist: google>=3.0.0
Requires-Dist: google-genai>=1.36.0
Requires-Dist: litellm>=1.77.1
Requires-Dist: platformdirs>=4.4.0
Requires-Dist: psutil>=6.0.0
Requires-Dist: python-dotenv==1.1.0
Requires-Dist: tomli-w>=1.2.0
Requires-Python: >=3.10
Project-URL: Homepage, https://github.com/WeismannS/proto-agent
Project-URL: Issues, https://github.com/WeismannS/proto-agent/issues
Project-URL: Repository, https://github.com/WeismannS/proto-agent
